<?xml version="1.0" encoding="utf-8"?>
<!DOCTYPE hibernate-mapping PUBLIC "-//Hibernate/Hibernate Mapping DTD 3.0//EN"
                                   "http://hibernate.sourceforge.net/hibernate-mapping-3.0.dtd">
<!-- 
    Mapping file autogenerated by MyEclipse Persistence Tools
-->
<hibernate-mapping>
 <class name="org.monster.entity.Books" table="books">
  <id name="isbn" type="java.lang.String">
   <column length="50" name="isbn"/>
   <generator class="assigned"/>
  </id>
  <property generated="never" lazy="false" name="title" type="java.lang.String">
   <column length="50" name="title">
    <comment>书名</comment>
   </column>
  </property>
  <property generated="never" lazy="false" name="publisherName" type="java.lang.String">
   <column length="200" name="publisherName">
    <comment>出版社名称</comment>
   </column>
  </property>
  <property generated="never" lazy="false" name="price" type="java.lang.Double">
   <column name="price" precision="9">
    <comment>书籍单价</comment>
   </column>
  </property>
  <property generated="never" lazy="false" name="pubDt" type="java.util.Date">
   <column length="10" name="pubDt">
    <comment>出版日期</comment>
   </column>
  </property>
 </class>
</hibernate-mapping>
